datasette_jupyterlite/__init__.py
datasette_jupyterlite-0.1a1.dist-info/METADATA
datasette_jupyterlite-0.1a1.dist-info/WHEEL
datasette_jupyterlite-0.1a1.dist-info/entry_points.txt
datasette_jupyterlite-0.1a1.dist-info/top_level.txt
datasette_jupyterlite-0.1a1.dist-info/RECORD
