Metadata-Version: 2.1
Name: datasette-jupyterlite
Version: 0.1a1
Summary: JupyterLite as a Datasette plugin
Home-page: https://github.com/simonw/datasette-jupyterlite
Author: Simon Willison
License: Apache License, Version 2.0
Project-URL: Issues, https://github.com/simonw/datasette-jupyterlite/issues
Project-URL: CI, https://github.com/simonw/datasette-jupyterlite/actions
Project-URL: Changelog, https://github.com/simonw/datasette-jupyterlite/releases
Platform: UNKNOWN
Requires-Python: >=3.7
Requires-Dist: datasette
Requires-Dist: jupyterlite
Requires-Dist: importlib-resources
Provides-Extra: test
Requires-Dist: pytest ; extra == 'test'
Requires-Dist: pytest-asyncio ; extra == 'test'
